ts_tokenizer/__init__.py
ts_tokenizer/char_fix.py
ts_tokenizer/cli.py
ts_tokenizer/data.py
ts_tokenizer/date_check.py
ts_tokenizer/emoticon_check.py
ts_tokenizer/inner_punc.py
ts_tokenizer/punctuation_process.py
ts_tokenizer/smiley_check.py
ts_tokenizer/token_handler.py
ts_tokenizer/tokenizer.py
ts_tokenizer/unit_test.py
ts_tokenizer/data/TS_Corpus_Turkish_Word_List.txt
ts_tokenizer/data/abbr_list.txt
ts_tokenizer/data/cand_abbr_list.txt
ts_tokenizer/data/corection_mark.txt
ts_tokenizer/data/currency_symbols.txt
ts_tokenizer/data/domains.txt
ts_tokenizer/data/emoticons.txt
ts_tokenizer/data/eng_word_list.txt
ts_tokenizer/data/exceptions.txt
ts_tokenizer/data/smileys.txt
ts_tokenizer-0.1.20.dist-info/LICENSE
ts_tokenizer-0.1.20.dist-info/METADATA
ts_tokenizer-0.1.20.dist-info/WHEEL
ts_tokenizer-0.1.20.dist-info/entry_points.txt
ts_tokenizer-0.1.20.dist-info/top_level.txt
ts_tokenizer-0.1.20.dist-info/RECORD
