Metadata-Version: 2.1
Name: ts-tokenizer
Version: 0.1.20
Summary: TS Tokenizer is a hybrid (lexicon-based and rule-based) tokenizer designed specifically for tokenizing Turkish texts.
Home-page: https://github.com/tanerim/ts_tokenizer
Author: Taner Sezer
Author-email: tanersezerr@gmail.com
License: MIT
Project-URL: Bug Tracker, https://github.com/tanerim/ts_tokenizer/issues
Project-URL: Documentation, https://github.com/tanerim/ts_tokenizer#readme
Project-URL: Source Code, https://github.com/tanerim/ts_tokenizer
Keywords: turkish tokenizer,tokenizer,turkish,nlp,text-processing,language-processing
Classifier: Development Status :: 4 - Beta
Classifier: Programming Language :: Python :: 3
Classifier: Programming Language :: Python :: 3.9
Classifier: Programming Language :: Python :: 3.10
Classifier: Programming Language :: Python :: 3.11
Classifier: Programming Language :: Python :: 3.12
Classifier: License :: OSI Approved :: MIT License
Classifier: Natural Language :: Turkish
Classifier: Topic :: Text Processing :: Linguistic
Classifier: Operating System :: OS Independent
Requires-Python: >=3.9
License-File: LICENSE
Requires-Dist: tqdm ~=4.66.4
